diveplane/upgrade/LICENSE-3RD-PARTY.txt
diveplane/upgrade/__init__.py
diveplane/upgrade/__main__.py
diveplane/upgrade/requirements-3.10.txt
diveplane/upgrade/requirements-3.11.txt
diveplane/upgrade/requirements-3.8.txt
diveplane/upgrade/requirements-3.9.txt
diveplane/upgrade/requirements-dev-3.10.txt
diveplane/upgrade/requirements-dev-3.11.txt
diveplane/upgrade/requirements-dev-3.8.txt
diveplane/upgrade/requirements-dev-3.9.txt
diveplane/upgrade/requirements-dev.in
diveplane/upgrade/requirements.in
diveplane/upgrade/upgrade_utils.py
diveplane_upgrader-0.0.10.dist-info/LICENSE.txt
diveplane_upgrader-0.0.10.dist-info/METADATA
diveplane_upgrader-0.0.10.dist-info/WHEEL
diveplane_upgrader-0.0.10.dist-info/entry_points.txt
diveplane_upgrader-0.0.10.dist-info/top_level.txt
diveplane_upgrader-0.0.10.dist-info/RECORD
